solradm/__init__.py
solradm/main.py
solradm/update.py
solradm/api/__init__.py
solradm/api/cores.py
solradm/api/models.py
solradm/api/state.py
solradm/api/utils/__init__.py
solradm/commands/__init__.py
solradm/commands/collections/__init__.py
solradm/commands/config/__init__.py
solradm/commands/core/__init__.py
solradm/commands/core/cores.py
solradm/commands/zk/__init__.py
solradm/commands/zk/editor.py
solradm/commands/zk/utils/__init__.py
solradm/commands/zk/utils/sync_handler.py
solradm/commands/zk/utils/znode_copier.py
solradm/config/__init__.py
solradm/config/context.py
solradm/config/util.py
solradm/config/interactive/__init__.py
solradm/config/interactive/setup_context.py
solradm/config/interactive/setup_solrauth.py
solradm/exceptions/__init__.py
solradm/exceptions/adm_exception.py
solradm/exceptions/solr_exception.py
solradm/kube/__init__.py
solradm/kube/utils.py
solradm/renderers/__init__.py
solradm/renderers/renderer.py
solradm/renderers/task_table.py
solradm/tasks/__init__.py
solradm/tasks/metatask.py
solradm/tasks/multimetatask.py
solradm/zk/__init__.py
solradm/zk/utils.py
solradm-0.9.0.dist-info/METADATA
solradm-0.9.0.dist-info/WHEEL
solradm-0.9.0.dist-info/entry_points.txt
solradm-0.9.0.dist-info/top_level.txt
solradm-0.9.0.dist-info/RECORD
