Metadata-Version: 2.4
Name: solradm
Version: 0.9.0
Summary: Solr Administration CLI
Requires-Python: >=3.13
Requires-Dist: aiohttp==3.12.15
Requires-Dist: async-typer>=0.1.9
Requires-Dist: dynaconf>=3.2.4
Requires-Dist: kazoo>=2.10.0
Requires-Dist: kubernetes>=33.1.0
Requires-Dist: lazy-loader>=0.4
Requires-Dist: platformdirs>=4.3.8
Requires-Dist: pydantic>=2.11.7
Requires-Dist: pyyaml>=6.0.2
Requires-Dist: typer>=0.16.0
Requires-Dist: watchdog>=6.0.0
